[
  {
    "img": "https://preview.colorlib.com/theme/ezuca/images/1.jpg",
    "title": "Full Stack Development",
    "duration": 6,
    "description": "Master frontend and backend  with modern frameworks and databases."
  },
  {
    "img": "https://preview.colorlib.com/theme/ezuca/images/2.jpg",
    "title": "Web Development with AI & Python",
    "duration": 5,
    "description": "Build intelligent web applications by integrating AI and Python automation."
  },
  {
    "img": "https://preview.colorlib.com/theme/ezuca/images/3.jpg",
    "title": "Frontend Development with React",
    "duration": 3,
    "description": "Learn React, TailwindCSS, and modern UI practices for professional frontends."
  },
  {
    "img": "https://preview.colorlib.com/theme/ezuca/images/4.jpg",
    "title": "Data Science & Machine Learning",
    "duration": 6,
    "description": "Gain skills in data analysis, visualization, and machine learning algorithms."
  }
]
